Workbook

Sheet Assunzioni
A1: ANALISI FINANZIARIA — STRATEGIA DI LANCIO PRIVATIO
A3: PARAMETRI DI INPUT (celle gialle = modificabili)
A5: Mix agenzie per tier | B5: % del totale | C5: Prezzo medio €/mese | D5: Max agenzie/zona | E5: Note
A6: BASE (comuni <20k) | B6: 0.55 | C6: 374 | D6: 3.5 | E6: €249-499/mese
A7: URBANA (città 20k-100k) | B7: 0.3 | C7: 749 | D7: 5 | E7: €499-999/mese
A8: PREMIUM (centri storici) | B8: 0.15 | C8: 1800 | D8: 5.5 | E8: €999-2.600/mese
A9: Prezzo medio ponderato €/mese | B9: =B6*C6+B7*C7+B8*C8 -> 700.4
A11: ACQUISIZIONE AGENZIE (primi 12 mesi)
A12: Parametro | B12: Valore | C12: Unità | E12: Note
A13: Agenzie target mese 1 (free trial) | B13: 15 | C13: agenzie | E13: Obiettivo conservativo primo mese
A14: Crescita mensile agenzie (mesi 2-3 free) | B14: 8 | C14: agenzie/mese | E14: Passaparola durante trial
A15: Crescita mensile agenzie (mesi 4-12 a pagamento) | B15: 5 | C15: agenzie/mese | E15: Crescita organica post-trial
A16: Tasso conversione free→paid | B16: 0.25 | C16: % | E16: Benchmark SaaS B2B: 15-30%
A17: Churn mensile post-conversione | B17: 0.05 | C17: % | E17: Benchmark SaaS B2B: 3-7%
A18: Sconto anno 1 (proposta Federico) | B18: 0.2 | C18: % | E18: 20% riduzione tariffe primo anno
A19: Costi fissi mensili (server, tools, ecc.) | B19: 150 | C19: €/mese | E19: Vercel Pro + Supabase + tools
A20: Costi marketing mensile | B20: 300 | C20: €/mese | E20: Social ads, contenuti, outreach
A21: Costi una tantum lancio | B21: 1500 | C21: € | E21: Legale, P.IVA, setup iniziale

Sheet A - Prezzo Pieno
A1: SCENARIO A — PREZZO PIENO DAL MESE 1 (no trial, no sconti)
B2: Mese 1 | C2: Mese 2 | D2: Mese 3 | E2: Mese 4 | F2: Mese 5 | G2: Mese 6 | H2: Mese 7 | I2: Mese 8 | J2: Mese 9 | K2: Mese 10 | L2: Mese 11 | M2: Mese 12 | N2: TOTALE 12 MESI
A3: Nuove agenzie iscritte | B3: 8 | C3: 4 | D3: 4 | E3: 4 | F3: 4 | G3: 4 | H3: 4 | I3: 4 | J3: 4 | K3: 4 | L3: 4 | M3: 4 | N3: =SUM(B3:M3) -> 52
A4: Agenzie che abbandonano (churn 5%) | B4: 0 | C4: =ROUND(B5*Assunzioni!B17,0) -> 0 | D4: =ROUND(C5*Assunzioni!B17,0) -> 1 | E4: =ROUND(D5*Assunzioni!B17,0) -> 1 | F4: =ROUND(E5*Assunzioni!B17,0) -> 1 | G4: =ROUND(F5*Assunzioni!B17,0) -> 1 | H4: =ROUND(G5*Assunzioni!B17,0) -> 1 | I4: =ROUND(H5*Assunzioni!B17,0) -> 1 | J4: =ROUND(I5*Assunzioni!B17,0) -> 2 | K4: =ROUND(J5*Assunzioni!B17,0) -> 2 | L4: =ROUND(K5*Assunzioni!B17,0) -> 2 | M4: =ROUND(L5*Assunzioni!B17,0) -> 2 | N4: =SUM(B4:M4) -> 14
A5: Agenzie attive (paganti) | B5: =B3 -> 8 | C5: =B5+C3-C4 -> 12 | D5: =C5+D3-D4 -> 15 | E5: =D5+E3-E4 -> 18 | F5: =E5+F3-F4 -> 21 | G5: =F5+G3-G4 -> 24 | H5: =G5+H3-H4 -> 27 | I5: =H5+I3-I4 -> 30 | J5: =I5+J3-J4 -> 32 | ... M5: =L5+M3-M4 -> 38 | N5: =M5 -> 38
A7: RICAVI
A8: Revenue mensile (prezzo pieno) | B8: =B5*Assunzioni!B9 -> 5603.2 | C8: =C5*Assunzioni!B9 -> 8404.8 | D8: =D5*Assunzioni!B9 -> 10506 | E8: =E5*Assunzioni!B9 -> 12607.2 | F8: =F5*Assunzioni!B9 -> 14708.4 | G8: =G5*Assunzioni!B9 -> 16809.6 | H8: =H5*Assunzioni!B9 -> 18910.8 | I8: =I5*Assunzioni!B9 -> 21012 | J8: =J5*Assunzioni!B9 -> 22412.8 | K8: =K5*Assunzioni!B9 -> 23813.6 | L8: =L5*Assunzioni!B9 -> 25214.4 | M8: =M5*Assunzioni!B9 -> 26615.2 | N8: =SUM(B8:M8) -> 206618
A10: COSTI
A11: Costi fissi (server, tools) | B11: =Assunzioni!B19 -> 150 | C11: =Assunzioni!B19 -> 150 | D11: =Assunzioni!B19 -> 150 | E11: =Assunzioni!B19 -> 150 | F11: =Assunzioni!B19 -> 150 | G11: =Assunzioni!B19 -> 150 | H11: =Assunzioni!B19 -> 150 | I11: =Assunzioni!B19 -> 150 | J11: =Assunzioni!B19 -> 150 | K11: =Assunzioni!B19 -> 150 | L11: =Assunzioni!B19 -> 150 | M11: =Assunzioni!B19 -> 150 | N11: =SUM(B11:M11) -> 1800
A12: Costi marketing | B12: =Assunzioni!B20 -> 300 | C12: =Assunzioni!B20 -> 300 | D12: =Assunzioni!B20 -> 300 | E12: =Assunzioni!B20 -> 300 | F12: =Assunzioni!B20 -> 300 | G12: =Assunzioni!B20 -> 300 | H12: =Assunzioni!B20 -> 300 | I12: =Assunzioni!B20 -> 300 | J12: =Assunzioni!B20 -> 300 | K12: =Assunzioni!B20 -> 300 | L12: =Assunzioni!B20 -> 300 | M12: =Assunzioni!B20 -> 300 | N12: =SUM(B12:M12) -> 3600
A13: Costi una tantum lancio | B13: =Assunzioni!B21 -> 1500 | C13: 0 | D13: 0 | E13: 0 | F13: 0 | G13: 0 | H13: 0 | I13: 0 | J13: 0 | K13: 0 | L13: 0 | M13: 0 | N13: =SUM(B13:M13) -> 1500
A14: Totale costi | B14: =B11+B12+B13 -> 1950 | C14: =C11+C12+C13 -> 450 | D14: =D11+D12+D13 -> 450 | E14: =E11+E12+E13 -> 450 | F14: =F11+F12+F13 -> 450 | G14: =G11+G12+G13 -> 450 | H14: =H11+H12+H13 -> 450 | I14: =I11+I12+I13 -> 450 | ... M14: =M11+M12+M13 -> 450 | N14: =SUM(B14:M14) -> 6900
A16: MARGINE
A17: Profitto/Perdita mensile | B17: =B8-B14 -> 3653.2 | C17: =C8-C14 -> 7954.8 | D17: =D8-D14 -> 10056 | E17: =E8-E14 -> 12157.2 | F17: =F8-F14 -> 14258.4 | G17: =G8-G14 -> 16359.6 | H17: =H8-H14 -> 18460.8 | I17: =I8-I14 -> 20562 | ... M17: =M8-M14 -> 26165.2 | N17: =SUM(B17:M17) -> 199718
A18: Profitto/Perdita cumulativo | B18: =B17 -> 3653.2 | C18: =B18+C17 -> 11608 | D18: =C18+D17 -> 21664 | E18: =D18+E17 -> 33821.2 | F18: =E18+F17 -> 48079.6 | G18: =F18+G17 -> 64439.2 | H18: =G18+H17 -> 82900 | I18: =H18+I17 -> 103462 | J18: =I18+J17 -> 125424.8 | ... M18: =L18+M17 -> 199718 | N18: =M18 -> 199718

Sheet B - Tua Proposta
A1: SCENARIO B — 3 MESI FREE + 20% SCONTO ANNO 1 (proposta Federico)
B2: Mese 1 | C2: Mese 2 | D2: Mese 3 | E2: Mese 4 | F2: Mese 5 | G2: Mese 6 | H2: Mese 7 | I2: Mese 8 | J2: Mese 9 | K2: Mese 10 | L2: Mese 11 | M2: Mese 12 | N2: TOTALE 12 MESI
A3: Nuove agenzie iscritte | B3: =Assunzioni!B13 -> 15 | C3: =Assunzioni!B14 -> 8 | D3: =Assunzioni!B14 -> 8 | E3: =Assunzioni!B15 -> 5 | F3: =Assunzioni!B15 -> 5 | G3: =Assunzioni!B15 -> 5 | H3: =Assunzioni!B15 -> 5 | I3: =Assunzioni!B15 -> 5 | J3: =Assunzioni!B15 -> 5 | K3: =Assunzioni!B15 -> 5 | L3: =Assunzioni!B15 -> 5 | M3: =Assunzioni!B15 -> 5 | N3: =SUM(B3:M3) -> 76
A4: Di cui in periodo free (mesi 1-3) | B4: =B5 -> 15 | C4: =C5 -> 23 | D4: =D5 -> 31 | E4: 0 | F4: 0 | G4: 0 | H4: 0 | I4: 0 | J4: 0 | K4: 0 | L4: 0 | M4: 0 | N4: =SUM(B4:M4) -> 69
A5: Agenzie attive totali | B5: =B3 -> 15 | C5: =B5+C3 -> 23 | D5: =C5+D3 -> 31 | E5: =ROUND(D5*Assunzioni!B16,0)+E3 -> 13 | F5: =E5+F3-ROUND(E5*Assunzioni!B17,0) -> 17 | G5: =F5+G3-ROUND(F5*Assunzioni!B17,0) -> 21 | H5: =G5+H3-ROUND(G5*Assunzioni!B17,0) -> 25 | I5: =H5+I3-ROUND(H5*Assunzioni!B17,0) -> 29 | J5: =I5+J3-ROUND(I5*Assunzioni!B17,0) -> 33 | K5: =J5+K3-ROUND(J5*Assunzioni!B17,0) -> 36 | L5: =K5+L3-ROUND(K5*Assunzioni!B17,0) -> 39 | M5: =L5+M3-ROUND(L5*Assunzioni!B17,0) -> 42 | N5: =M5 -> 42
A6: Di cui paganti (80% prezzo) | B6: 0 | C6: 0 | D6: 0 | E6: =E5 -> 13 | F6: =F5 -> 17 | G6: =G5 -> 21 | H6: =H5 -> 25 | I6: =I5 -> 29 | J6: =J5 -> 33 | K6: =K5 -> 36 | L6: =L5 -> 39 | M6: =M5 -> 42 | N6: =M6 -> 42
A8: RICAVI
A9: Revenue mensile (prezzo scontato -20%) | B9: =B6*Assunzioni!B9*(1-Assunzioni!B18) -> 0 | C9: =C6*Assunzioni!B9*(1-Assunzioni!B18) -> 0 | D9: =D6*Assunzioni!B9*(1-Assunzioni!B18) -> 0 | E9: =E6*Assunzioni!B9*(1-Assunzioni!B18) -> 7284.16 | F9: =F6*Assunzioni!B9*(1-Assunzioni!B18) -> 9525.44 | G9: =G6*Assunzioni!B9*(1-Assunzioni!B18) -> 11766.72 | H9: =H6*Assunzioni!B9*(1-Assunzioni!B18) -> 14008 | I9: =I6*Assunzioni!B9*(1-Assunzioni!B18) -> 16249.28 | J9: =J6*Assunzioni!B9*(1-Assunzioni!B18) -> 18490.56 | K9: =K6*Assunzioni!B9*(1-Assunzioni!B18) -> 20171.52 | L9: =L6*Assunzioni!B9*(1-Assunzioni!B18) -> 21852.48 | M9: =M6*Assunzioni!B9*(1-Assunzioni!B18) -> 23533.44 | N9: =SUM(B9:M9) -> 142881.6
A11: COSTI
A12: Costi fissi (server, tools) | B12: =Assunzioni!B19 -> 150 | C12: =Assunzioni!B19 -> 150 | D12: =Assunzioni!B19 -> 150 | E12: =Assunzioni!B19 -> 150 | F12: =Assunzioni!B19 -> 150 | G12: =Assunzioni!B19 -> 150 | H12: =Assunzioni!B19 -> 150 | I12: =Assunzioni!B19 -> 150 | J12: =Assunzioni!B19 -> 150 | K12: =Assunzioni!B19 -> 150 | L12: =Assunzioni!B19 -> 150 | M12: =Assunzioni!B19 -> 150 | N12: =SUM(B12:M12) -> 1800
A13: Costi marketing | B13: =Assunzioni!B20 -> 300 | C13: =Assunzioni!B20 -> 300 | D13: =Assunzioni!B20 -> 300 | E13: =Assunzioni!B20 -> 300 | F13: =Assunzioni!B20 -> 300 | G13: =Assunzioni!B20 -> 300 | H13: =Assunzioni!B20 -> 300 | I13: =Assunzioni!B20 -> 300 | J13: =Assunzioni!B20 -> 300 | K13: =Assunzioni!B20 -> 300 | L13: =Assunzioni!B20 -> 300 | M13: =Assunzioni!B20 -> 300 | N13: =SUM(B13:M13) -> 3600
A14: Costi una tantum lancio | B14: =Assunzioni!B21 -> 1500 | C14: 0 | D14: 0 | E14: 0 | F14: 0 | G14: 0 | H14: 0 | I14: 0 | J14: 0 | K14: 0 | L14: 0 | M14: 0 | N14: =SUM(B14:M14) -> 1500
A15: Totale costi | B15: =B12+B13+B14 -> 1950 | C15: =C12+C13+C14 -> 450 | D15: =D12+D13+D14 -> 450 | E15: =E12+E13+E14 -> 450 | F15: =F12+F13+F14 -> 450 | G15: =G12+G13+G14 -> 450 | H15: =H12+H13+H14 -> 450 | I15: =I12+I13+I14 -> 450 | ... M15: =M12+M13+M14 -> 450 | N15: =SUM(B15:M15) -> 6900
A17: MARGINE
A18: Profitto/Perdita mensile | B18: =B9-B15 -> -1950 | C18: =C9-C15 -> -450 | D18: =D9-D15 -> -450 | E18: =E9-E15 -> 6834.16 | F18: =F9-F15 -> 9075.44 | G18: =G9-G15 -> 11316.72 | H18: =H9-H15 -> 13558 | I18: =I9-I15 -> 15799.28 | ... M18: =M9-M15 -> 23083.44 | N18: =SUM(B18:M18) -> 135981.6
A19: Profitto/Perdita cumulativo | B19: =B18 -> -1950 | C19: =B19+C18 -> -2400 | D19: =C19+D18 -> -2850 | E19: =D19+E18 -> 3984.16 | F19: =E19+F18 -> 13059.6 | G19: =F19+G18 -> 24376.32 | H19: =G19+H18 -> 37934.32 | I19: =H19+I18 -> 53733.6 | J19: =I19+J18 -> 71774.16 | ... M19: =L19+M18 -> 135981.6 | N19: =M19 -> 135981.6

Sheet C - Alternativa Consigliata
A1: SCENARIO C — 3 MESI FREE + "PREZZO FONDATORE" BLOCCATO (no sconto esplicito)
B2: Mese 1 | C2: Mese 2 | D2: Mese 3 | E2: Mese 4 | F2: Mese 5 | G2: Mese 6 | H2: Mese 7 | I2: Mese 8 | J2: Mese 9 | K2: Mese 10 | L2: Mese 11 | M2: Mese 12 | N2: TOTALE 12 MESI
A3: Nuove agenzie iscritte | B3: =Assunzioni!B13 -> 15 | C3: =Assunzioni!B14 -> 8 | D3: =Assunzioni!B14 -> 8 | E3: =Assunzioni!B15 -> 5 | F3: =Assunzioni!B15 -> 5 | G3: =Assunzioni!B15 -> 5 | H3: =Assunzioni!B15 -> 5 | I3: =Assunzioni!B15 -> 5 | J3: =Assunzioni!B15 -> 5 | K3: =Assunzioni!B15 -> 5 | L3: =Assunzioni!B15 -> 5 | M3: =Assunzioni!B15 -> 5 | N3: =SUM(B3:M3) -> 76
A4: Di cui in periodo free (mesi 1-3) | B4: =B5 -> 15 | C4: =C5 -> 23 | D4: =D5 -> 31 | E4: 0 | F4: 0 | G4: 0 | H4: 0 | I4: 0 | J4: 0 | K4: 0 | L4: 0 | M4: 0 | N4: =SUM(B4:M4) -> 69
A5: Agenzie attive totali | B5: =B3 -> 15 | C5: =B5+C3 -> 23 | D5: =C5+D3 -> 31 | E5: =ROUND(D5*0.3,0)+E3 -> 14 | F5: =E5+F3-ROUND(E5*Assunzioni!B17,0) -> 18 | G5: =F5+G3-ROUND(F5*Assunzioni!B17,0) -> 22 | H5: =G5+H3-ROUND(G5*Assunzioni!B17,0) -> 26 | I5: =H5+I3-ROUND(H5*Assunzioni!B17,0) -> 30 | J5: =I5+J3-ROUND(I5*Assunzioni!B17,0) -> 33 | K5: =J5+K3-ROUND(J5*Assunzioni!B17,0) -> 36 | L5: =K5+L3-ROUND(K5*Assunzioni!B17,0) -> 39 | M5: =L5+M3-ROUND(L5*Assunzioni!B17,0) -> 42 | N5: =M5 -> 42
A6: Di cui paganti (prezzo fondatore = -10%) | B6: 0 | C6: 0 | D6: 0 | E6: =E5 -> 14 | F6: =F5 -> 18 | G6: =G5 -> 22 | H6: =H5 -> 26 | I6: =I5 -> 30 | J6: =J5 -> 33 | K6: =K5 -> 36 | L6: =L5 -> 39 | M6: =M5 -> 42 | N6: =M6 -> 42
A8: RICAVI
A9: Revenue mensile (prezzo fondatore -10%) | B9: =B6*Assunzioni!B9*0.9 -> 0 | C9: =C6*Assunzioni!B9*0.9 -> 0 | D9: =D6*Assunzioni!B9*0.9 -> 0 | E9: =E6*Assunzioni!B9*0.9 -> 8825.04 | F9: =F6*Assunzioni!B9*0.9 -> 11346.48 | G9: =G6*Assunzioni!B9*0.9 -> 13867.92 | H9: =H6*Assunzioni!B9*0.9 -> 16389.36 | I9: =I6*Assunzioni!B9*0.9 -> 18910.8 | J9: =J6*Assunzioni!B9*0.9 -> 20801.88 | K9: =K6*Assunzioni!B9*0.9 -> 22692.96 | L9: =L6*Assunzioni!B9*0.9 -> 24584.04 | M9: =M6*Assunzioni!B9*0.9 -> 26475.12 | N9: =SUM(B9:M9) -> 163893.6
A11: COSTI
A12: Costi fissi (server, tools) | B12: =Assunzioni!B19 -> 150 | C12: =Assunzioni!B19 -> 150 | D12: =Assunzioni!B19 -> 150 | E12: =Assunzioni!B19 -> 150 | F12: =Assunzioni!B19 -> 150 | G12: =Assunzioni!B19 -> 150 | H12: =Assunzioni!B19 -> 150 | I12: =Assunzioni!B19 -> 150 | J12: =Assunzioni!B19 -> 150 | K12: =Assunzioni!B19 -> 150 | L12: =Assunzioni!B19 -> 150 | M12: =Assunzioni!B19 -> 150 | N12: =SUM(B12:M12) -> 1800
A13: Costi marketing | B13: =Assunzioni!B20 -> 300 | C13: =Assunzioni!B20 -> 300 | D13: =Assunzioni!B20 -> 300 | E13: =Assunzioni!B20 -> 300 | F13: =Assunzioni!B20 -> 300 | G13: =Assunzioni!B20 -> 300 | H13: =Assunzioni!B20 -> 300 | I13: =Assunzioni!B20 -> 300 | J13: =Assunzioni!B20 -> 300 | K13: =Assunzioni!B20 -> 300 | L13: =Assunzioni!B20 -> 300 | M13: =Assunzioni!B20 -> 300 | N13: =SUM(B13:M13) -> 3600
A14: Costi una tantum lancio | B14: =Assunzioni!B21 -> 1500 | C14: 0 | D14: 0 | E14: 0 | F14: 0 | G14: 0 | H14: 0 | I14: 0 | J14: 0 | K14: 0 | L14: 0 | M14: 0 | N14: =SUM(B14:M14) -> 1500
A15: Totale costi | B15: =B12+B13+B14 -> 1950 | C15: =C12+C13+C14 -> 450 | D15: =D12+D13+D14 -> 450 | E15: =E12+E13+E14 -> 450 | F15: =F12+F13+F14 -> 450 | G15: =G12+G13+G14 -> 450 | H15: =H12+H13+H14 -> 450 | I15: =I12+I13+I14 -> 450 | ... M15: =M12+M13+M14 -> 450 | N15: =SUM(B15:M15) -> 6900
A17: MARGINE
A18: Profitto/Perdita mensile | B18: =B9-B15 -> -1950 | C18: =C9-C15 -> -450 | D18: =D9-D15 -> -450 | E18: =E9-E15 -> 8375.04 | F18: =F9-F15 -> 10896.48 | G18: =G9-G15 -> 13417.92 | H18: =H9-H15 -> 15939.36 | I18: =I9-I15 -> 18460.8 | ... M18: =M9-M15 -> 26025.12 | N18: =SUM(B18:M18) -> 156993.6
A19: Profitto/Perdita cumulativo | B19: =B18 -> -1950 | C19: =B19+C18 -> -2400 | D19: =C19+D18 -> -2850 | E19: =D19+E18 -> 5525.04 | F19: =E19+F18 -> 16421.52 | G19: =F19+G18 -> 29839.44 | H19: =G19+H18 -> 45778.8 | I19: =H19+I18 -> 64239.6 | J19: =I19+J18 -> 84591.48 | ... M19: =L19+M18 -> 156993.6 | N19: =M19 -> 156993.6

Sheet Confronto Scenari
A1: CONFRONTO SCENARI — RIEPILOGO 12 MESI
A3: Metrica | B3: A: Prezzo Pieno | C3: B: Tua Proposta | D3: C: Alternativa | E3: Differenza B vs A
A4: Agenzie iscritte (totale 12 mesi) | B4: ='A - Prezzo Pieno'!N3 -> 52 | C4: ='B - Tua Proposta'!N3 -> 76 | D4: ='C - Alternativa Consigliata'!N3 -> 76 | E4: =C4-B4 -> 24
A5: Agenzie attive al mese 12 | B5: ='A - Prezzo Pieno'!N5 -> 38 | C5: ='B - Tua Proposta'!N5 -> 42 | D5: ='C - Alternativa Consigliata'!N5 -> 42 | E5: =C5-B5 -> 4
A6: Revenue totale 12 mesi | B6: ='A - Prezzo Pieno'!N8 -> 206618 | C6: ='B - Tua Proposta'!N9 -> 142881.6 | D6: ='C - Alternativa Consigliata'!N9 -> 163893.6 | E6: =C6-B6 -> -63736.4
A7: Costi totali 12 mesi | B7: ='A - Prezzo Pieno'!N14 -> 6900 | C7: ='B - Tua Proposta'!N15 -> 6900 | D7: ='C - Alternativa Consigliata'!N15 -> 6900 | E7: =C7-B7 -> 0
A8: Profitto/Perdita 12 mesi | B8: ='A - Prezzo Pieno'!N17 -> 199718 | C8: ='B - Tua Proposta'!N18 -> 135981.6 | D8: ='C - Alternativa Consigliata'!N18 -> 156993.6 | E8: =C8-B8 -> -63736.4
A9: Mesi in perdita (Scenario A) | B9: =COUNTIF('A - Prezzo Pieno'!B17:M17,"<0") -> 0
A10: Mesi in perdita (Scenario B) | C10: =COUNTIF('B - Tua Proposta'!B18:M18,"<0") -> 3
A11: Mesi in perdita (Scenario C) | D11: =COUNTIF('C - Alternativa Consigliata'!B18:M18,"<0") -> 3
A13: RACCOMANDAZIONE
A14: Lo Scenario C (3 mesi free + prezzo fondatore bloccato al -10%) offre il miglior equilibrio:
A15: 1. Stessa capacità di acquisizione del free trial (risolve il chicken-and-egg)
A16: 2. Revenue più alta vs Scenario B grazie allo sconto ridotto (10% vs 20%)
A17: 3. Migliore percezione: "prezzo fondatore bloccato" > "sconto 20%" (framing psicologico)
A18: 4. Conversione attesa più alta (30% vs 25%) grazie al framing di esclusività
A19: 5. Transizione al prezzo pieno più naturale (il prezzo fondatore resta, i nuovi pagano di più)
